openfhe/__init__.py
openfhe/build-config.txt
openfhe/openfhe.cpython-312-x86_64-linux-gnu.so
openfhe/lib/libOPENFHEbinfhe.so.1
openfhe/lib/libOPENFHEcore.so.1
openfhe/lib/libOPENFHEpke.so.1
openfhe/lib/libgomp.so
openfhe-1.4.2.0.24.4.dist-info/licenses/LICENSE
openfhe-1.4.2.0.24.4.dist-info/METADATA
openfhe-1.4.2.0.24.4.dist-info/WHEEL
openfhe-1.4.2.0.24.4.dist-info/top_level.txt
openfhe-1.4.2.0.24.4.dist-info/RECORD
