Metadata-Version: 2.4
Name: openfhe
Version: 1.4.2.0.24.4
Summary: Python wrapper for OpenFHE C++ library.
Home-page: https://github.com/openfheorg/openfhe-python
Author: OpenFHE Team
Author-email: contact@openfhe.org
License: BSD-2-Clause
Classifier: Operating System :: POSIX :: Linux
Classifier: Operating System :: MacOS :: MacOS X
Requires-Python: >=3.12
License-File: LICENSE
Dynamic: author
Dynamic: author-email
Dynamic: classifier
Dynamic: description
Dynamic: description-content-type
Dynamic: home-page
Dynamic: license
Dynamic: license-file
Dynamic: requires-python
Dynamic: summary
